{"name":"Seebrise","tagline":"A fruitful desktop environment for the touch-typing enthusiast","body":"Seebrise\r\n========\r\n\r\nIt would be far fetched to call Seebrise an actual desktop environment. I use\r\nthe following set-up on a laptop and two stand-alone PCs each running (L)ubuntu\r\nas the underlying core system.  The following installation instruction, though,\r\nshould work with any flavour of Linux. Instead of running LXDE, I use the\r\ntiling window manager [herbustluftwm](http://www.herbstluftwm.org/) with a\r\n[tint2](http://www.herbstluftwm.org/) panel.  Together with a custom Dvorak\r\nkeyboard layout variant for easy programming, typing umlauts, and tailored to a\r\nnon-staggered keyboard -- such as the Kinesis Advantage Ergonomic Keyboard (see\r\nthe dx-file) -- it yields a fruitful touch-typing environment.\r\n\r\n![screenshot][screenshot]\r\n\r\nInstallation process\r\n====================\r\n\r\nPackages\r\n--------\r\n\r\nHaving a freshly installed vanilla Lubuntu in front of you, you need to install\r\nthe following packages.\r\n\r\n```\r\n# apt-get install git vim-gtk zsh tmux herbstluftwm tint2 dmenu feh mupdf xdotool unclutter\r\n```\r\n\r\nClone the dotfiles from this repository\r\n---------------------------------------\r\n\r\n```\r\n% git clone https://github.com/00tau/dotfiles.git ~/.dotfiles\r\n% cd .dotfiles\r\n% git submodule update --init --recursive\r\n% ./create-links\r\n% ln -s ~/.dotfiles/tint2 ~/.config/tint2\r\n% ln -s ~/.dotfiles/herbstluftwm ~/.config/herbstluftwm\r\n% mkdir ~/.tmp # for vim's backup files\r\n```\r\n\r\nMake Zsh your primary shell\r\n---------------------------\r\n\r\n```\r\n$ which zsh\r\n$ chsh\r\n```\r\n\r\nAdd Seebrise to your xsessions\r\n------------------------------\r\n\r\n```\r\n# cp seebrise.desktop /usr/share/xsessions/\r\n```\r\n\r\nDvoraX\r\n------------------------------------------------------\r\n\r\nA Dvorak keyboard layout tailored to non-staggerd keyboards with a grid layout.\r\nExamples are the\r\n[Kinesis Advantage](https://www.kinesis-ergo.com/shop/advantage-for-pc-mac/),\r\n[Key64](http://www.key64.org), or the [ErgoDox](http://ergodox.org/).\r\n\r\n```\r\n# ln -s ~/.dotfiles/dx /usr/share/X11/xkb/symbols/dx\r\n```\r\n\r\nFirefox\r\n-------\r\n\r\nDon't forget to get the coolest Add-On to Firefox: [Pentadactyl](http://5digits.org/pentadactyl/)\r\n\r\n[screenshot]: https://lh3.googleusercontent.com/-sTswtdTJSn8/VUoppqaEcTI/AAAAAAAAAKM/8DOzbbkGxkI/w506-h285/test.png\r\n","google":"","note":"Don't delete this file! It's used internally to help with page regeneration."}